mlcbase/__init__.py
mlcbase/conifg.py
mlcbase/database.py
mlcbase/email.py
mlcbase/emoji_pbar.py
mlcbase/encrypt_password.py
mlcbase/entrypt_aes.py
mlcbase/entrypt_rsa.py
mlcbase/file.py
mlcbase/image_io.py
mlcbase/loading.py
mlcbase/logger.py
mlcbase/misc.py
mlcbase/otp.py
mlcbase/register.py
mlcbase/remote_connect.py
mlcbase/timer.py
mlcbase/vault.py
mlcbase-1.2.11.dist-info/LICENSE
mlcbase-1.2.11.dist-info/METADATA
mlcbase-1.2.11.dist-info/WHEEL
mlcbase-1.2.11.dist-info/top_level.txt
mlcbase-1.2.11.dist-info/RECORD
