Metadata-Version: 2.2
Name: mlcbase
Version: 1.2.11
Summary: The base module of all MuLingCloud modules and applications.
Author-email: Weiming Chen <wmchen@mulingcloud.com>, Yuanshuang Sun <sunsun5544@126.com>
License:                                  Apache License
Project-URL: Homepage, https://www.mulingcloud.com
Project-URL: Repository, https://github.com/mulingcloud/mlcbase.git
Classifier: Operating System :: Microsoft :: Windows
Classifier: Operating System :: POSIX :: Linux
Classifier: Operating System :: MacOS
Classifier: Programming Language :: Python
Requires-Python: >=3.7
License-File: LICENSE
Requires-Dist: packaging
Requires-Dist: rich
Requires-Dist: colorama
Requires-Dist: loguru
Requires-Dist: pytz
Requires-Dist: pyyaml
Requires-Dist: toml
Requires-Dist: pycryptodome
Requires-Dist: psutil
Requires-Dist: requests
Requires-Dist: paramiko
Requires-Dist: PyMySQL
Requires-Dist: pyotp
Requires-Dist: qrcode[pil]
Requires-Dist: opencv-python
Requires-Dist: matplotlib
Requires-Dist: ipython
